vlpi/__init__.py
vlpi/vLPI.py
vlpi/data/ClinicalDataSimulator.py
vlpi/data/ClinicalDataset.py
vlpi/data/ICDUtilities.py
vlpi/data/__init__.py
vlpi/data/ICDData/ICD10_Chapters.txt
vlpi/data/ICDData/icd10_ukbb.txt
vlpi/data/ICDData/icd10cm_order_2018.txt
vlpi/model/Decoders.py
vlpi/model/Encoders.py
vlpi/model/FCLayers.py
vlpi/model/VAE.py
vlpi/model/__init__.py
vlpi/optim/Optimizer.py
vlpi/optim/__init__.py
vlpi/utils/FeatureSelection.py
vlpi/utils/LinearPositiveWeights.py
vlpi/utils/UtilityFunctions.py
vlpi/utils/__init__.py
vlpi-0.1.8.dist-info/LICENSE
vlpi-0.1.8.dist-info/METADATA
vlpi-0.1.8.dist-info/WHEEL
vlpi-0.1.8.dist-info/top_level.txt
vlpi-0.1.8.dist-info/RECORD
