Metadata-Version: 2.1
Name: vlpi
Version: 0.1.8
Summary: Python implementation of the variational latent phenotype model described in Blair et al..
Home-page: https://github.com/daverblair/vlpi
Author: David Blair
Author-email: david.blair@ucsf.edu
License: UNKNOWN
Platform: UNKNOWN
Classifier: Programming Language :: Python :: 3
Classifier: License :: OSI Approved :: MIT License
Classifier: Operating System :: OS Independent
License-File: LICENSE
Requires-Dist: torch (==1.5.1)
Requires-Dist: pyro-ppl (>=1.3.1)
Requires-Dist: numpy (>=1.19.0)
Requires-Dist: pandas (>=1.0.5)
Requires-Dist: scipy (>=1.5.2)
Requires-Dist: scikit-learn (>=0.22.1)
Requires-Dist: typing
Requires-Dist: unidecode
